rohub/__init__.py
rohub/_version.py
rohub/memo.py
rohub/rohub.py
rohub/settings.py
rohub/utils.py
rohub/ResearchObject/ResearchObject.py
rohub/ResearchObject/__init__.py
rohub-0.3.0.dist-info/LICENSE
rohub-0.3.0.dist-info/METADATA
rohub-0.3.0.dist-info/WHEEL
rohub-0.3.0.dist-info/top_level.txt
rohub-0.3.0.dist-info/RECORD
