Metadata-Version: 2.1
Name: rohub
Version: 0.3.0
Summary: Rohub is a high-level, user-friendly Python API for working with Research Objects.
Home-page: https://git.man.poznan.pl/stash/projects/ROHUB/repos/rohub2020-jupyter-notebooks/browse?at=refs%2Fheads%2Fmaster
Author: Bogusz Janiak
Author-email: bjaniak@man.poznan.pl
License: UNKNOWN
Platform: UNKNOWN
Classifier: Programming Language :: Python :: 3
Classifier: License :: OSI Approved :: MIT License
Classifier: Operating System :: OS Independent
Requires-Python: >=3.6
License-File: LICENSE
Requires-Dist: requests
